Metadata-Version: 1.1
Name: ipspan
Version: 0.1
Summary: A library for summarizing groups of IP Addresses
Home-page: https://github.com/tifoster/ipspan
Author: Tim Foster Gusba
Author-email: tifoster@akamai.com
License: UNKNOWN
Keywords: ip address addresses range span readability summary
Platform: UNKNOWN
Classifier: Development Status :: 3 - Alpha
Classifier: Intended Audience :: Developers
Classifier: Topic :: Software Development :: Libraries :: Python Modules
Classifier: License :: OSI Approved :: MIT License
Classifier: Programming Language :: Python :: 3
Classifier: Programming Language :: Python :: 3.4
Classifier: Programming Language :: Python :: 3.5
Classifier: Programming Language :: Python :: 3.6
